README.md
pyembedpg.py
setup.cfg
setup.py
pyembedpg.egg-info/PKG-INFO
pyembedpg.egg-info/SOURCES.txt
pyembedpg.egg-info/dependency_links.txt
pyembedpg.egg-info/requires.txt
pyembedpg.egg-info/top_level.txt