Metadata-Version: 1.1
Name: pyembedpg
Version: 0.0.4
Summary: Run embedded version of Postgres
Home-page: http://github.com/simulmedia/pyembedpg/
Author: Simulmedia
Author-email: francois@simulmedia.com
License: Apache License 2.0
Keywords: postgres,python,tests
Platform: UNKNOWN
Classifier: License :: OSI Approved :: Apache Software License
Classifier: Topic :: Software Development :: Libraries :: Python Modules
Classifier: Programming Language :: Python
Classifier: Programming Language :: Python :: 2
Classifier: Programming Language :: Python :: 2.6
Classifier: Programming Language :: Python :: 2.7
Classifier: Programming Language :: Python :: 3
Classifier: Programming Language :: Python :: 3.3
Classifier: Programming Language :: Python :: 3.4
Classifier: Programming Language :: Python :: 3.6
Classifier: Programming Language :: Python :: 3.7
